Metadata-Version: 2.1
Name: wtussiw
Version: 0.0.1
Summary: some function for rpa_application 
Author: Yu.linxing
Author-email: linxing_1@163.com
